{"1942":true,"007 - The World is Not Enough":true,"10-Pin Bowling":true,"102 Dalmatians - Puppies to the Rescue":true,"3-D Ultra Pinball - Thrillride":true,"3D Pocket Pool":true,"4-in-1 Funpak":true,"4-in-1 Funpak Vol. II":true,"720 Degrees":true,"Action Man - Search for Base X":true,"Addams Family, The":true,"Addams Family, The - Pugsley's Scavenger Hunt":true,"Adventure Island":true,"Adventure Island II":true,"Adventures of Lolo":true,"Adventures of Rocky and Bullwinkle, The":true,"Adventures of Star Saver, The":true,"Adventures of the Smurfs, The":true,"Aero Star":true,"Agro Soar":true,"AirForce Delta":true,"Aladdin":true,"Alfred Chicken":true,"Alice in Wonderland":true,"Alien 3":true,"Alien Olympics 2044 AD":true,"Alien vs Predator - The Last of His Clan":true,"Aliens - Thanatos Encounter":true,"All Star Tennis 2000":true,"All-Star Baseball '99":true,"All-Star Baseball 2000":true,"All-Star Baseball 2001":true,"Alleyway":true,"Alone in the Dark - The New Nightmare":true,"Altered Space":true,"Amazing Penguin":true,"Amazing Spider-Man 2, The":true,"Amazing Spider-Man 3, The - Invasion of the Spider-Slayers":true,"Amazing Spider-Man, The":true,"Amazing Tater":true,"Animaniacs":true,"Animorphs":true,"Antz":true,"Antz Racing":true,"Antz World Sportz":true,"Armada - FX Racers":true,"Armorines - Project S.W.A.R.M.":true,"Army Men - Air Combat":true,"Army Men - Sarge's Heroes 2":true,"Army Men 2":true,"Arthur's Absolutely Fun Day!":true,"Asterix":true,"Asterix & Obelix vs Caesar":true,"Asterix - Search for Dogmatix":true,"Asteroids":true,"Asteroids & Missile Command":true,"Atlantis - The Lost Empire":true,"Atomic Punk":true,"Attack of the Killer Tomatoes":true,"Austin Powers - Oh, Behave!":true,"Austin Powers - Welcome to My Underground Lair!":true,"Avenging Spirit":true,"Azure Dreams":true,"B.C. Kid":true,"Baby Felix - Halloween":true,"Baby T-Rex":true,"Backgammon":true,"Ballistic":true,"Balloon Kid":true,"Barbie - Fashion Pack Games":true,"Barbie - Game Girl":true,"Barbie - Magic Genie Adventure":true,"Barbie - Pet Rescue":true,"Barbie - Shelly Club":true,"Barca Total 2000":true,"Baseball":true,"Bases Loaded":true,"Bass Masters Classic":true,"Bataille Navale":true,"Batman":true,"Batman - Return of the Joker":true,"Batman - The Animated Series":true,"Batman Beyond - Return of the Joker":true,"Batman Forever":true,"Battle Arena Toshinden":true,"Battle Bull":true,"Battle Tanx":true,"Battle Unit Zeoth":true,"Battle Zone & Super Breakout":true,"Battle of Olympus, The":true,"Battleship":true,"Battletoads":true,"Battletoads Double Dragon - The Ultimate Team":true,"Battletoads in Ragnarok's World":true,"Bear in the Big Blue House":true,"Beauty and the Beast - A Board Game Adventure":true,"Beavis and Butt-head":true,"Beetlejuice":true,"Benjamin Bluemchen - Ein Verrueckter Tag im Zoo":true,"Berlitz French Language Translator":true,"Berlitz Spanish Language Translator":true,"Best of the Best - Championship Karate":true,"Bibi Blocksberg - Im Bann der Hexenkugel":true,"Bibi und Tina - Fohlen Felix in Gefahr":true,"Bill & Ted's Excellent Gameboy Adventure":true,"Bill Elliott's NASCAR Fast Tracks":true,"Billy Bob's Huntin' 'n' Fishin'":true,"Bionic Battler":true,"Bionic Commando":true,"Bionic Commando - Elite Forces":true,"Black Bass - Lure Fishing":true,"Blade":true,"Blades of Steel":true,"Blaster Master - Enemy Below":true,"Blaster Master Boy":true,"Blue's Clues - Blue's Alphabet Book":true,"Blues Brothers, The":true,"Blues Brothers, The - Jukebox Adventure":true,"Bo Jackson Hit and Run":true,"Bob the Builder - Fix It Fun!":true,"Boggle Plus":true,"Bomb Jack":true,"Bomberman Max":true,"Bomberman Quest":true,"Bonk's Adventure":true,"Bonk's Revenge":true,"Boomer's Adventure in ASMIK World":true,"Boulder Dash":true,"Boxxle":true,"Boxxle 2":true,"Boy and His Blob, A - The Rescue of Princess Blobette":true,"Brain Drain":true,"Brainbender":true,"Bram Stoker's Dracula":true,"BreakThru!":true,"Bubble Bobble":true,"Bubble Bobble Part 2":true,"Bubble Ghost":true,"Bubsy 2":true,"Buffy the Vampire Slayer":true,"Bugs Bunny":true,"Bugs Bunny & Lola Bunny - Carrot Crazy":true,"Bugs Bunny - Crazy Castle 3":true,"Bugs Bunny - Crazy Castle 4":true,"Bugs Bunny - Crazy Castle II":true,"Burai Fighter Deluxe":true,"Burger Time Deluxe":true,"Bust-A-Move 2 - Arcade Edition":true,"Bust-A-Move 3 DX":true,"Bust-A-Move 4":true,"Bust-A-Move Millennium":true,"Buster Brothers":true,"Buzz Lightyear of Star Command":true,"Caesars Palace":true,"Caesars Palace II":true,"Cannon Fodder":true,"Captain America and the Avengers":true,"Carl Lewis Athletics 2000":true,"Carmageddon":true,"Casino Funpak":true,"Casper":true,"Castelian":true,"Castle Quest":true,"Castlevania - Legends":true,"Castlevania Adventure, The":true,"Castlevania II - Belmont's Revenge":true,"Caterpillar Construction Zone":true,"Catrap":true,"Catwoman":true,"Championship Motocross 2001 featuring Ricky Carmichael":true,"Championship Pool":true,"Chase H.Q.":true,"Chessmaster, The":true,"Chicken Run":true,"Choplifter II - Rescue & Survive":true,"Choplifter III":true,"Chuck Rock":true,"Cliffhanger":true,"Colin McRae Rally":true,"College Slam":true,"Conker's Pocket Tales":true,"Contra - The Alien Wars":true,"Cool Bricks":true,"Cool Spot":true,"Cool World":true,"Cosmo Tank":true,"Croc":true,"Croc 2":true,"Cross Country Racing":true,"Cruis'n Exotica":true,"Cutthroat Island":true,"Cyber Tiger":true,"Cyraid":true,"Daedalean Opus":true,"Daffy Duck - Fowl Play":true,"Daffy Duck - The Marvin Missions":true,"Daikatana":true,"Darkman":true,"Darkwing Duck":true,"Das Geheimnis der Happy Hippo-Insel":true,"Dave Mirra Freestyle BMX":true,"David Beckham Soccer":true,"Days of Thunder":true,"Dead Heat Scramble":true,"Deer Hunter":true,"Defender-Joust":true,"Deja Vu I & II":true,"Denki Blocks!":true,"Dennis the Menace":true,"Desert Strike - Return to the Gulf":true,"Dexter's Laboratory - Robot Rampage":true,"Dexterity":true,"Dick Tracy":true,"Dig Dug":true,"Dinosaur":true,"Dinosaur'us":true,"Disney's Tarzan":true,"Diva Starz - Mall Mania":true,"Donald Duck - Quack Attack":true,"Donald Duck in Maui Mallard":true,"Donkey Kong":true,"Donkey Kong Country":true,"Donkey Kong Land":true,"Donkey Kong Land 2":true,"Donkey Kong Land III":true,"Double Dragon":true,"Double Dragon 2":true,"Double Dragon 3":true,"Double Dribble - 5 on 5":true,"Doug's Big Game":true,"Dr. Franken":true,"Dr. Franken II":true,"Dr. Mario":true,"Dracula - Crazy Vampire":true,"Dragon Dance":true,"Dragon Heart":true,"Dragon Tales - Dragon Adventures":true,"Dragon Tales - Dragon Wings":true,"Dragon Warrior I & II":true,"Dragon Warrior III":true,"Dragon Warrior Monsters":true,"Dragon Warrior Monsters 2":true,"Dragon's Lair":true,"Dragon's Lair - The Legend":true,"Driver - You Are The Wheelman":true,"Dropzone":true,"Duck Tales":true,"Duck Tales 2":true,"Duke Nukem":true,"Dukes of Hazzard, The - Racing for Home":true,"E.T. The Extra Terrestrial - Digital Companion":true,"E.T. The Extra Terrestrial - Escape from Planet Earth":true,"E.T. The Extra Terrestrial and the Cosmic Garden":true,"E.T. The Extra-Terrestrial and the Cosmic Garden":true,"ECW Hardcore Revolution":true,"ESPN International Track & Field":true,"ESPN National Hockey Night":true,"Earthworm Jim":true,"Earthworm Jim - Menace 2 the Galaxy":true,"Elevator Action":true,"Elite Soccer":true,"Elmo in Grouchland":true,"Elmo's 123s":true,"Elmo's ABCs":true,"Emperor's New Groove, The":true,"Evel Knievel":true,"Extra Bases!":true,"Extreme Ghostbusters":true,"F-1 Pole Position":true,"F-1 Race":true,"F-1 Racing Championship":true,"F-1 World Grand Prix II":true,"F-15 Strike Eagle":true,"F.A. Premier League Stars 2001, The":true,"F1 Championship Season 2000":true,"FIFA 2000":true,"FIFA Soccer '96":true,"FIFA Soccer '97":true,"FIFA Soccer '98 - Road to the World Cup":true,"Faceball 2000":true,"Fastest Lap":true,"Felix the Cat":true,"Ferrari - Grand Prix Challenge":true,"Fidgetts, The":true,"Fighting Simulator 2in1 - Flying Warriors":true,"Final Fantasy Adventure":true,"Final Fantasy Legend II":true,"Final Fantasy Legend III":true,"Final Fantasy Legend, The":true,"Fire Fighter":true,"Fish Dude":true,"Fist of the North Star":true,"Fix & Foxi - Episode 1 Lupo":true,"Flash, The":true,"Flintstones, The":true,"Flintstones, The - Burgertime in Bedrock":true,"Flintstones, The - King Rock Treasure Island":true,"Flipper & Lopaka":true,"Flipull":true,"Football International":true,"Force 21":true,"Foreman for Real":true,"Formula One 2000":true,"Fort Boyard":true,"Fortified Zone":true,"Frank Thomas' Big Hurt Baseball":true,"Frogger":true,"Frogger 2":true,"Frommer's Personal Organizer":true,"Frommer's Travel Guide":true,"Galaga & Galaxian":true,"Galaga - Destination Earth":true,"Game & Watch Gallery":true,"Game & Watch Gallery 2":true,"Game & Watch Gallery 3":true,"Game of Harmony, The":true,"Gameboy Camera":true,"Ganbare Goemon - Tengutou no Gyakushuu":true,"Gargoyle's Quest - Ghosts'n Goblins":true,"Gauntlet II":true,"Gear Works":true,"George Foreman's KO Boxing":true,"Getaway, The":true,"Gex - Enter the Gecko":true,"Gex 3 - Deep Cover Gecko":true,"Ghostbusters II":true,"Ghosts 'N Goblins":true,"Go! Go! Tank":true,"Goal!":true,"Gobs of Games":true,"Godzilla":true,"Godzilla - The Series":true,"Gold and Glory - The Road to El Dorado":true,"Golf":true,"Gradius - The Interstellar Assault":true,"Grand Prix":true,"Grand Theft Auto":true,"Grand Theft Auto 2":true,"Great Greed":true,"Gremlins 2 - The New Batch":true,"Gremlins Unleashed":true,"Grinch, The":true,"Gute Zeiten Schlechte Zeiten Quiz":true,"Hal Wrestling":true,"Halloween Racer":true,"Hammerin' Harry - Ghost Building Company":true,"Hamtaro - Ham-Hams Unite!":true,"Hands of Time":true,"Harley-Davidson - Race Across America":true,"Harry Potter and The Chamber of Secrets":true,"Harry Potter and The Sorcerer's Stone":true,"Harvest Moon 2 GBC":true,"Harvest Moon 3 GBC":true,"Harvest Moon GB":true,"Hatris":true,"Heavyweight Championship Boxing":true,"Heiankyo Alien":true,"Hello Kitty's Cube Frenzy":true,"Hercules - The Legendary Journeys":true,"Heroes of Might and Magic":true,"Heroes of Might and Magic II":true,"Hexcite - The Shapes of Victory":true,"High Stakes Gambling":true,"Hit the Ice":true,"Hole in One Golf":true,"Home Alone":true,"Home Alone 2":true,"Hook":true,"Hot Wheels - Stunt Track Driver":true,"Houghton Mifflin Spell Checker and Calculator":true,"Hoyle Card Games":true,"Hoyle Casino":true,"Hudson Hawk":true,"Hugo - Black Diamond Fever":true,"Hugo 2":true,"Hugo 2.5":true,"Humans, The":true,"Hunchback of Notre Dame, The - Topsy Turvy Games":true,"Hunt for Red October, The":true,"Hype - The Time Quest":true,"Hyper Lode Runner":true,"In Your Face":true,"Incredible Crash Dummies, The":true,"Indiana Jones and the Infernal Machine":true,"Indiana Jones and the Last Crusade":true,"InfoGenius Systems - Personal Organizer":true,"Inspector Gadget - Operation Madkactus":true,"International Karate":true,"International Rally":true,"International Superstar Soccer '99":true,"International Superstar Soccer 2000":true,"International Track & Field":true,"Ironman - X-O Manowar in Heavy Metal":true,"Ishido":true,"Itchy & Scratchy - Miniature Golf Madness":true,"Jack Nicklaus Golf":true,"James Bond 007":true,"Janosch - Das grosse Panama-Spiel":true,"Jeep Jamboree":true,"Jeff Gordon XS Racing":true,"Jelly Boy":true,"Jeopardy!":true,"Jeremy McGrath Supercross 2000":true,"Jetsons, The":true,"Jimmy Connors Tennis":true,"Jimmy White's Cueball":true,"Joe & Mac":true,"Joe & Mac - Caveman Ninja":true,"Jordan vs Bird - One-on-One":true,"Joust & Defender":true,"Judge Dredd":true,"Jungle Book, The":true,"Jungle Book, The - Mowgli's Wild Adventure":true,"Jungle Strike":true,"Jurassic Park":true,"Jurassic Park 2 - The Chaos Continues":true,"Kaept'n Blaubaer - Die verrueckte Schatzsuche":true,"Keep the Balance":true,"Kelly Club - Clubhouse Fun":true,"Ken Griffey Jr. Presents Major League Baseball":true,"Ken Griffey Jr.'s Slugfest":true,"Kid Dracula":true,"Kid Icarus - Of Myths and Monsters":true,"Killer Instinct":true,"King of Fighters '95, The":true,"King of Fighters, The - Heat of Battle":true,"Kingdom Crusade":true,"Kirby's Block Ball":true,"Kirby's Dream Land":true,"Kirby's Dream Land 2":true,"Kirby's Pinball Land":true,"Kirby's Star Stacker":true,"Kirby's Tilt 'n' Tumble":true,"Kirikou":true,"Klax":true,"Klustar":true,"Knight Quest":true,"Knockout Kings":true,"Koenig der Loewen, Der - Simbas grosses Abenteuer":true,"Konami GB Collection Vol.1":true,"Konami GB Collection Vol.2":true,"Konami GB Collection Vol.3":true,"Konami GB Collection Vol.4":true,"Koto Battle - Tengai no Morihito":true,"Kung-Fu Master":true,"Kwirk":true,"LEGO Alpha Team":true,"LEGO Island 2 - The Brickster's Revenge":true,"LEGO Racers":true,"LEGO Stunt Rally":true,"Lamborghini American Challenge":true,"Land Before Time, The":true,"Las Vegas Cool Hand":true,"Last Action Hero":true,"Laura":true,"Lawnmower Man, The":true,"Lazlos' Leap":true,"Legend of Zelda, The - Link's Awakening":true,"Legend of Zelda, The - Oracles":true,"Legend of the River King 2":true,"Legend of the River King GB":true,"Lemmings":true,"Lemmings & Oh No! More Lemmings":true,"Lemmings 2 - The Tribes":true,"Les Aventures De TinTin - Le Temple du Soleil":true,"Lethal Weapon":true,"Lil' Monster":true,"Lingo":true,"Lion King, The":true,"Lion King, The - Simba's Mighty Adventure":true,"Little Mermaid II, The - Pinball Frenzy":true,"Little Mermaid, The":true,"Little Nicky":true,"Lock 'N Chase":true,"Logical":true,"Looney Tunes":true,"Looney Tunes Collector - Alert!":true,"Looney Tunes Racing":true,"Loopz":true,"Lost World, The - Jurassic Park":true,"Lucky Luke":true,"Lucky Luke - Desperado Train":true,"Lufia - The Legend Returns":true,"M&M's Minis Madness":true,"MTV Sports - Pure Ride":true,"MTV Sports - Skateboarding featuring Andy MacDonald":true,"MTV Sports - T.J. Lavin's Ultimate BMX":true,"Madden '95":true,"Madden '96":true,"Madden '97":true,"Madden NFL 2000":true,"Madden NFL 2001":true,"Madden NFL 2002":true,"Magi Nation":true,"Magical Drop":true,"Magical Tetris Challenge":true,"Magnetic Soccer":true,"Malibu Beach Volleyball":true,"Marble Madness":true,"Mario Golf":true,"Mario Tennis":true,"Mario's Picross":true,"Maru's Mission":true,"Marvin Strikes Back!":true,"Mary-Kate & Ashley - Crush Course":true,"Mary-Kate & Ashley - Get a Clue!":true,"Mary-Kate & Ashley - Pocket Planner":true,"Mat Hoffman's Pro BMX":true,"Matchbox - Emergency Patrol":true,"Maus, Die":true,"Maus, Die - Verrueckte Olympiade":true,"Maya the Bee - Garden Adventures":true,"Megalit":true,"Megaman - Dr. Wily's Revenge":true,"Megaman II":true,"Megaman III":true,"Megaman IV":true,"Megaman V":true,"Megaman Xtreme":true,"Megaman Xtreme 2":true,"Men In Black - The Series":true,"Men In Black 2 - The Series":true,"Mercenary Force":true,"Merlin":true,"Metal Gear Solid":true,"Metal Masters":true,"Metal Walker":true,"Metroid II - Return of Samus":true,"Mia Hamm Soccer Shootout":true,"Mickey Mouse - Magic Wand":true,"Mickey's Dangerous Chase":true,"Mickey's Speedway USA":true,"Mickey's Ultimate Challenge":true,"Micro Machines":true,"Micro Machines 1 and 2 - Twin Turbo":true,"Micro Machines 2":true,"Micro Machines V3":true,"Micro Maniacs":true,"Microsoft Entertainment Pack":true,"Mighty Morphin Power Rangers":true,"Millipede - Centipede":true,"Milon's Secret Castle":true,"Miner 2049er":true,"Missile Command":true,"Mission Impossible":true,"Mole Mania":true,"Momotarou Dengeki":true,"Monkey Puncher":true,"Monopoly":true,"Monster Max":true,"Monster Rancher Battle Card GB":true,"Monster Rancher Explorer":true,"Monster Truck Wars":true,"Monsters, Inc.":true,"Montezuma's Return":true,"Moomin's Tale":true,"Moon Patrol & Spy Hunter":true,"Moorhuhn 2 - Die Jagd geht weiter":true,"Mortal Kombat":true,"Mortal Kombat 3":true,"Mortal Kombat 4":true,"Mortal Kombat I & II":true,"Mortal Kombat II":true,"Motocross Maniacs":true,"Motocross Maniacs 2":true,"Mousetrap Hotel":true,"Mr Nutz":true,"Mr. Chin's Gourmet Paradise":true,"Mr. Do!":true,"Mr. Driller":true,"Ms. Pac-Man":true,"Ms. Pac-Man Special Color Edition":true,"Muhammad Ali's Boxing":true,"Mummy Returns, The":true,"Mummy, The":true,"Muppets, The":true,"Mysterium":true,"Mystical Ninja":true,"NASCAR Challenge":true,"NASCAR Heat":true,"NASCAR Racers":true,"NBA 3 on 3 featuring Kobe Bryant":true,"NBA All Star Challenge":true,"NBA All Star Challenge 2":true,"NBA Hoopz":true,"NBA In The Zone 2000":true,"NBA Jam":true,"NBA Jam - Tournament Edition":true,"NBA Live 96":true,"NBA Showtime - NBA on NBC":true,"NFL Blitz":true,"NFL Blitz 2001":true,"NFL Football":true,"NFL Quarterback Club":true,"NFL Quarterback Club 2":true,"NFL Quarterback Club 96":true,"NHL Blades of Steel 2000":true,"NHL Hockey '96":true,"NSYNC - Get to the Show":true,"NYR - New York Race":true,"Nail'N Scale":true,"Nations, The - Land of Legends":true,"Navy Seals":true,"Nemesis":true,"New Adventures of Mary-Kate & Ashley, The":true,"New Batman Adventures, The - Chaos in Gotham":true,"Nicktoons Racing":true,"Nigel Mansell's World Championship '92":true,"Ninja Boy":true,"Ninja Boy 2":true,"Ninja Gaiden Shadow":true,"Nintendo World Cup":true,"No Fear - Downhill Mountain Biking":true,"Nobunaga's Ambition":true,"Noddy and the Birthday Party":true,"O'Leary Manager 2000":true,"Oddworld Adventures":true,"Oddworld Adventures II":true,"Operation C":true,"Original Moorhuhn Jagd, Die":true,"Othello":true,"Ottifanten - Kommando Stoertebeker":true,"Otto's Ottifanten":true,"Out of Gas":true,"Pac-Attack":true,"Pac-Man":true,"Pac-Man Special Color Edition":true,"Pac-Panic":true,"Pac-in-Time":true,"Pagemaster, The":true,"Palamedes":true,"Panel Action Bingo":true,"Pang":true,"Paperboy":true,"Paperboy 2":true,"Papyrus":true,"Parasol Stars":true,"Parodius":true,"Penguin Wars":true,"Perfect Dark":true,"Phantom Air Mission":true,"Pinball - Revenge of the Gator":true,"Pinball Deluxe":true,"Pinball Dreams":true,"Pinball Fantasies":true,"Pinball Mania":true,"Pingu - Sekai de 1ban Genki na Penguin":true,"Pinocchio":true,"Pipe Dream":true,"Pit Fighter":true,"Planet of the Apes":true,"Play Action Football":true,"Player Manager 2001":true,"Pocket Bowling":true,"Pocket Racing":true,"Pocket Soccer":true,"Pokemon - Blue Version":true,"Pokemon - Crystal Version":true,"Pokemon - Gold Version":true,"Pokemon - Green Version":true,"Pokemon - Red Version":true,"Pokemon - Silver Version":true,"Pokemon - Yellow Version":true,"Pokemon Pinball":true,"Pokemon Puzzle Challenge":true,"Pokemon Trading Card Game":true,"Polaris SnoCross":true,"Pong - The Next Level":true,"Pooh and Tigger's Hunny Safari":true,"Pop 'N TwinBee":true,"Pop Up":true,"Popeye 2":true,"Populous":true,"Portal Runner":true,"Power Mission":true,"Power Quest":true,"Power Racer":true,"Power Rangers - Lightspeed Rescue":true,"Power Rangers - Time Force":true,"Power Spike - Pro Beach Volleyball":true,"Powerpuff Girls, The - Bad Mojo Jojo":true,"Powerpuff Girls, The - Battle Him":true,"Powerpuff Girls, The - Paint the Townsville Green":true,"Prehistorik Man":true,"Primal Rage":true,"Prince Naseem Boxing":true,"Prince of Persia":true,"Pro Darts":true,"Pro Pool":true,"Project S-11":true,"Prophecy - The Viking Child":true,"Puchi Carat":true,"Pumuckl's Abenteuer bei den Piraten":true,"Pumuckl's Abenteuer im Geisterschloss":true,"Punisher, The - The Ultimate Payback":true,"Puzzle Master":true,"Puzzled":true,"Pyramids of Ra":true,"Q Billion":true,"Q-bert II":true,"Qix":true,"Qix Adventure":true,"Quarth":true,"Quest - Fantasy Challenge":true,"Quest RPG - Brian's Journey":true,"Quest for Camelot":true,"R-Type":true,"R-Type DX":true,"R-Type II":true,"Race Days":true,"Race Drivin'":true,"Radar Mission":true,"Raging Fighter":true,"Rainbow Islands":true,"Rampage - World Tour":true,"Rampage 2 - Universal Tour":true,"Rampart":true,"Rats!":true,"Rayman":true,"Rayman 2 - The Great Escape":true,"Razor Freestyle Scooter":true,"Ready 2 Rumble Boxing":true,"Real Ghostbusters, The":true,"Ren & Stimpy Show, The - Space Cadet Adventures":true,"Ren & Stimpy Show, The - Veediots!":true,"Rescue Heroes - Fire Frenzy":true,"Resident Evil Gaiden":true,"Return of the Ninja":true,"Revelations - The Demon Slayer":true,"Rhino Rumble":true,"Riddick Bowe Boxing":true,"Ring Rage":true,"Rip-Tide Racer":true,"Road Champs - BXS Stunt Biking":true,"Road Rash":true,"Robin Hood":true,"Robin Hood - Prince of Thieves":true,"RoboCop Vs. The Terminator":true,"Robocop":true,"Robocop 2":true,"Robocop Interactive Game":true,"Robopon":true,"Robot Wars - Metal Mayhem":true,"Rocket Power - Gettin' Air":true,"Rocky Mountain Trophy Hunter":true,"Rodland":true,"Roger Clemens MVP Baseball":true,"Rokumon Tengai Mon-Colle-Knight GB":true,"Rolan's Curse":true,"Rolan's Curse II":true,"Roland Garros French Open":true,"Ronaldo V.Soccer":true,"Roswell Conspiracies - Aliens, Myths & Legends":true,"Rox":true,"Rugrats - Time Travelers":true,"Rugrats - Totally Angelica":true,"Rugrats Movie, The":true,"Rugrats in Paris - The Movie":true,"SWIV":true,"Sabrina - The Animated Series - Spooked!":true,"Sabrina - The Animated Series - Zapped!":true,"San Francisco Rush 2049":true,"Santa Claus Junior":true,"Scooby-Doo! - Classic Creep Capers":true,"Scrabble":true,"Sea Battle":true,"SeaQuest DSV":true,"Sensible Soccer - European Champions":true,"Serpent":true,"Sgt. Rock - On The Front Line":true,"Shadowgate Classic":true,"Shamus":true,"Shanghai":true,"Shantae":true,"Shrek - Fairy Tale Freakdown":true,"Side Pocket":true,"Simpsons, The - Bart & the Beanstalk":true,"Simpsons, The - Bart vs the Juggernauts":true,"Simpsons, The - Escape from Camp Deadly":true,"Simpsons, The - Krusty's Fun House":true,"Simpsons, The - Night of the Living Treehouse of Horror":true,"Skate or Die - Bad 'N Rad":true,"Skate or Die - Tour de Thrash":true,"Small Soldiers":true,"Smurfs 3, The":true,"Smurfs, The":true,"Sneaky Snakes":true,"Snoopy - Magic Show":true,"Snoopy Tennis":true,"Snow Bros. Jr.":true,"Snow White and the Seven Dwarfs":true,"Soccer Manager":true,"Soccer Mania":true,"SolarStriker":true,"Solitaire Funpak":true,"Solomon's Club":true,"Space Invaders [C]":true,"Space Invaders [S]":true,"Space Marauder":true,"Spacestation Silicon Valley":true,"Spanky's Quest":true,"Spawn":true,"Speedball 2 - Brutal Deluxe":true,"Speedy Gonzales - Aztec Adventure":true,"Spider-Man":true,"Spider-Man 2 - The Sinister Six":true,"Spider-Man and the X-Men in Arcade's Revenge":true,"Spirit of F-1, The":true,"Spirou":true,"Spirou - La Panique Mecanique":true,"SpongeBob SquarePants - Legend of the Lost Spatula":true,"Sports Illustrated - Football & Baseball":true,"Sports Illustrated - Golf Classic":true,"Sports Illustrated for Kids - The Ultimate Triple Dare!":true,"Spot":true,"Spot - The Cool Adventure":true,"Spud's Adventure":true,"Spy vs. Spy":true,"Spy vs. Spy - Operation Boobytrap":true,"Square Deal - The Game of Two Dimensional Poker":true,"Star Trek - 25th Anniversary":true,"Star Trek - Generations - Beyond the Nexus":true,"Star Trek - The Next Generation":true,"Star Wars":true,"Star Wars - Super Return of the Jedi":true,"Star Wars - The Empire Strikes Back":true,"Star Wars Episode I - Obi-Wan's Adventures":true,"Star Wars Episode I - Racer":true,"Stargate":true,"Stop That Roach!":true,"Street Fighter Alpha - Warriors' Dreams":true,"Street Fighter II":true,"Street Racer":true,"Stuart Little - The Journey Home":true,"Sumo Fighter":true,"Super Battletank":true,"Super Black Bass":true,"Super Breakout!":true,"Super Chase H.Q.":true,"Super Hunchback":true,"Super James Pond":true,"Super Kick Off":true,"Super Mario Bros. Deluxe":true,"Super Mario Land":true,"Super Mario Land 2 - 6 Golden Coins":true,"Super Off Road":true,"Super R.C. Pro-Am":true,"Super Scrabble":true,"Supercross Freestyle":true,"Superman":true,"Survival Kids":true,"Suzuki Alstare Extreme Racing":true,"Swamp Thing":true,"Swing":true,"Sword of Hope II, The":true,"Sword of Hope, The":true,"Sylvester and Tweety":true,"T2 - The Arcade Game":true,"TNN Outdoors Fishing Champ":true,"TOCA Touring Car Championship":true,"Tabaluga":true,"Tail Gator":true,"Tale Spin":true,"Tamagotchi":true,"Tarzan":true,"Tasmania Story":true,"Taz-Mania":true,"Taz-Mania 2":true,"Tazmanian Devil - Munching Madness":true,"Tech Deck Skateboarding":true,"Tecmo Bowl":true,"Teenage Mutant Ninja Turtles - Back From the Sewers":true,"Teenage Mutant Ninja Turtles - Fall of the Foot Clan":true,"Teenage Mutant Ninja Turtles III - Radical Rescue":true,"Tennis":true,"Terminator 2 - Judgment Day":true,"Tesserae":true,"Test Drive 2001":true,"Test Drive 6":true,"Test Drive Cycles":true,"Test Drive Le Mans":true,"Test Drive Off-Road 3":true,"Tetris":true,"Tetris 2":true,"Tetris Attack":true,"Tetris Blast":true,"Tetris DX":true,"Tetris Plus":true,"Three Lions":true,"Tiger Woods PGA Tour 2000":true,"Tintin in Tibet":true,"Tiny Toon Adventures - Babs' Big Break":true,"Tiny Toon Adventures - Buster Saves the Day":true,"Tiny Toon Adventures - Dizzy's Candy Quest":true,"Tiny Toon Adventures - Wacky Sports":true,"Tiny Toon Adventures 2 - Montana's Movie Madness":true,"Tip Off":true,"Titus the Fox":true,"Toki Tori":true,"Tom Clancy's Rainbow Six":true,"Tom and Jerry":true,"Tom and Jerry - Frantic Antics":true,"Tom and Jerry - Mouse Hunt":true,"Tom and Jerry in Mouse Attacks!":true,"Tomb Raider":true,"Tomb Raider - Curse of the Sword":true,"Tonka Raceway":true,"Tony Hawk's Pro Skater":true,"Tony Hawk's Pro Skater 2":true,"Tony Hawk's Pro Skater 3":true,"Toobin'":true,"Toonsylvania":true,"Tootuff":true,"Top Gear Pocket":true,"Top Gear Pocket 2":true,"Top Gun - Fire Storm":true,"Top Gun - Guts & Glory":true,"Top Rank Tennis":true,"Top Ranking Tennis":true,"Torpedo Range":true,"Total Carnage":true,"Total Soccer 2000":true,"Towers - Lord Baniff's Deceit":true,"Toxic Crusaders":true,"Toy Story":true,"Toy Story 2":true,"Toy Story Racer":true,"Track & Field":true,"Track Meet":true,"Trax":true,"Trick Boarder":true,"Trip World":true,"Triple Play 2001":true,"Trouballs":true,"True Lies":true,"Tumble Pop":true,"Turn and Burn":true,"Turok - Battle of the Bionosaurs":true,"Turok - Rage Wars":true,"Turok 2 - Seeds of Evil":true,"Turok 3 - Shadow of Oblivion":true,"Turrican":true,"Tweenies - Doodles' Bones":true,"Tweety's High-Flying Adventure":true,"Tyco RC - Racin' Ratz":true,"Ultima - Runes of Virtue":true,"Ultima - Runes of Virtue II":true,"Ultimate Fighting Championship":true,"Ultimate Paint Ball":true,"Ultimate Surfing":true,"Ultra Golf":true,"Universal Soldier":true,"Uno":true,"Urban Strike":true,"V-Rally - Championship Edition":true,"VIP":true,"Vegas Games":true,"WCW Main Event":true,"WCW Mayhem":true,"WWF Attitude":true,"WWF Betrayal":true,"WWF King of the Ring":true,"WWF Raw":true,"WWF Superstars":true,"WWF Superstars 2":true,"WWF Warzone":true,"WWF WrestleMania 2000":true,"Wacky Races":true,"Walt Disney World Quest - Magical Racing Tour":true,"Wario Blast Featuring Bomberman!":true,"Wario Land - Super Mario Land 3":true,"Wario Land 3":true,"Wario Land II":true,"Warlocked":true,"Warriors of Might and Magic":true,"Water World":true,"Wave Race":true,"We're Back! - A Dinosaur's Story":true,"Wendy - Every Witch Way":true,"Wetrix GB":true,"Wheel of Fortune":true,"Who Framed Roger Rabbit":true,"Who Wants to Be a Millionaire - 2nd Edition":true,"Wild Thornberrys, The - Rambler":true,"Wings of Fury":true,"Winnie the Pooh - Adventures in the 100 Acre Wood":true,"Winter Gold":true,"Wizards & Warriors Chapter X - The Fortress of Fear":true,"Woody Woodpecker":true,"Woody Woodpecker Racing":true,"WordZap":true,"Wordtris":true,"World Bowling":true,"World Circuit Series":true,"World Cup USA '94":true,"World Destruction League - Thunder Tanks":true,"World Heroes 2 Jet":true,"Worms":true,"Worms Armageddon":true,"X-Men - Mutant Academy":true,"X-Men - Mutant Wars":true,"X-Men - Wolverine's Rage":true,"XVII Olympic Winter Games, The - Lillehammer 1994":true,"Xena - Warrior Princess":true,"Xenon 2 - Megablast":true,"Xtreme Sports":true,"Xtreme Wheels":true,"Yars' Revenge - The Quotile Ultimatum":true,"Yars' Revenge - The Quotile Ultimatum (PD)":true,"Yoda Stories":true,"Yogi Bear - Great Balloon Blast":true,"Yogi Bear in Yogi Bear's Goldrush":true,"Yoshi":true,"Yoshi's Cookie":true,"Your Virtual Petz Palz":true,"Yu-Gi-Oh! Dark Duel Stories":true,"Zebco Fishing!":true,"Zen - Intergalactic Ninja":true,"Zidane Football Generation":true,"Zoboomafoo - Playtime In Zobooland":true,"Zool":true,"Zoop":true}