{"Alchemist Marie & Elie - Futari no Atelier":true,"Anaza Hebun - Memory of Those Days":true,"Arc The Lad - Kijin Fukkatsu":true,"Bakusou Dekatora Densetsu":true,"Battle Spirit Digimon Frontier":true,"Beat Mania":true,"Blue Wing Blitz":true,"Card Captor Sakura - Sakura to Fushigi na Clow Card":true,"Chaos Gear - Michibi Kareshi Mono":true,"Cho Denki Card Battle Yofu Makai Kikuchi Shugo":true,"Choujikuu Yousai Macross - True Love Song":true,"Clock Tower":true,"Crazy Climber":true,"D's Garage 21 Koubo Game - Tane wo Maku Tori":true,"Dark Eyes - Battle Gate":true,"Dicing Knight Period":true,"Digimon Adventure 02 - D1 Tamers":true,"Digimon Adventure 02 - Tag Tamers":true,"Digimon Digital Monsters - D Project":true,"Digimon Digital Monsters for WonderSwanColor":true,"Digimon Tamers - Battle Spirit":true,"Digimon Tamers - Brave Tamer":true,"Digimon Tamers - Digimon Medley":true,"Digital Partner":true,"Dokodemo Hamster":true,"Dokodemo Hamster 3 - O Dekake Saffron":true,"Dragonball":true,"Engacho!":true,"Final Fantasy":true,"Final Fantasy II":true,"Final Fantasy IV":true,"Final Lap 2000":true,"Final Lap Special":true,"Flash - Koibito Kun":true,"From TV Animation - One Piece - Chopper no Daibouken":true,"From TV Animation - One Piece - Niji no Shima Densetsu":true,"From TV Animation - One Piece - Treasure Wars":true,"From TV Animation - One Piece - Treasure Wars 2 - Buggy Land e Youkoso":true,"Front Mission":true,"Ganso Jajamaru Kun":true,"Gekitou Crash Gear Turbo Gear Champion League":true,"Gensou Maden Saiyuuki Retribution":true,"Glocal Hexcite":true,"Golden Axe":true,"Gransta Chronicle":true,"Guilty Gear Petit":true,"Guilty Gear Petit 2":true,"GunPey Ex":true,"Hanafuda Shiyou Yo":true,"Hanjyuku Hero - Aah Sekai yo Hanjuku Nare":true,"Harobots":true,"Hataraku Chocobo":true,"Hunter X Hunter - Greed Island":true,"Hunter X Hunter - Ichi O Tsugu Mono":true,"Hunter X Hunter - Michibi Kareshi Mono":true,"Hunter X Hunter - Sorezore no Ketsui":true,"Inu Yasha":true,"Inu Yasha Fuu'un Emaki":true,"Inu Yasha Kagome no Yumenikki":true,"Itou Jun Ni Uzumaki Noroi Simulation":true,"Judgement Silversword - Rebirth Edition":true,"Keiba Yosou Shien Shinkaron":true,"Kidou Senshi Gundam Giren no Yabou Tokubetsuhen Aoki no Hasha":true,"Kidou Senshi Gundam Seed":true,"Kidou Senshi Gundam Vol.1 -Side 7-":true,"Kinniku Man Second Generations Dream Tag Match":true,"Kinnikuman Nisei Choujin Seisenshi":true,"Kosodate Quiz Doko de mo My Angel":true,"Kurupara!":true,"Langrisser Millenium WS - The Last Century":true,"Last Alive":true,"Lode Runner":true,"Magical Drop":true,"Mahjong Touryuumon":true,"Makai Toushi Sa-Ga":true,"Medarot - Perfect Edition":true,"Meitantei Conan - Majutsushi no Chousenjou!":true,"Meitantei Conan - Yugure no Koujo":true,"Memories of Festa":true,"Meta Communication Therapy nee Kiite!":true,"Mikeneko Holme's Ghost Panic":true,"Mobile Suit Gundam - Volume 2 - JABURO":true,"Mobile Suit Gundam MSVS":true,"Morita Shougi":true,"Mr. Driller":true,"Namco Super Wars":true,"Naruto":true,"Neon Genesis Evangelion Shito Ikusei":true,"Nice On":true,"Nobunaga no Yabo":true,"One Piece - Grand Battle Swan Colloseum":true,"Pocket no Naka no Doraemon":true,"Pro Mahjong Kiwame":true,"Puyo Puyo Tsu":true,"RUN=DIM Return to Earth":true,"Raku Jongg":true,"Rhyme Rider Kerorikan":true,"Ring Infinity":true,"Robot Works":true,"Rockman & Forte - Mirai Kara no Chousen Sha":true,"Rockman EXE N1 Battle":true,"Rockman EXE WS":true,"Romancing Saga":true,"SD Gundam - Emotional Jam":true,"SD Gundam - Operation U.C.":true,"SD Gundam Eiyuuden":true,"SD Gundam G Generation - Gather Beat 2":true,"SD Gundam G Generation - Mono-Eye Gundams":true,"SD Gundam Gashapon Senki - Episode 1":true,"Saint Seiya - Ougon Densetsu Hen Perfect Edition":true,"Senkaiden Ni - TV Animation Senkaiden Houshin Engi Yori":true,"Sennou Millenium":true,"Shaman King Mirai E no Ishi":true,"Shogi Touryuumon":true,"Side Pocket":true,"Slither Link":true,"Soroban Gu":true,"Space Invaders":true,"Star Hearts":true,"Star Hearts Taikenban":true,"Super Robot Taisen Compact":true,"Super Robot Taisen Compact 2":true,"Super Robot Taisen Compact 3":true,"Taikyoku Igo Heisei Kiin":true,"Tanjou - Debut":true,"Tare Pan no Gunpei":true,"Tekken Card Challenge":true,"Terrors 2":true,"Tetris":true,"Tetsuman":true,"Tokyo Majin Gakuen Fuju Fuuroku":true,"Tonpusou":true,"Trump Collection 2":true,"Trump Collection Bottom Up Teki Trump Seikatsu":true,"Turntablist - DJ Battle":true,"Uchuu Senkan Yamato":true,"Ultraman - Hikari no Kuni no Shisha":true,"Umizuri Ni Ikou":true,"Uzumaki - Denshi Kaiki Hen":true,"Vaitz Blade":true,"Wasabi Produce - Street Dancer":true,"Wild Card":true,"With You Mitsumete Itai":true,"Wizardry - Scenario 1 - Kyounou no Shiren Jou":true,"Wonder Classic":true,"Wondergate":true,"X - Card of Fate":true,"XI  Little":true,"Yakusoku no Chi Riviera":true}